{
    "wallpaper": "/home/birkhoff/Images/wallpaper/spiderverse.png",
    "alpha": "100",
    "special": {
        "background": "#0A171E",
        "foreground": "#cedbed",
        "cursor": "#cedbed"
    },
    "colors": {
        "color0": "#0A171E",
        "color1": "#446CAB",
        "color2": "#409FBC",
        "color3": "#4F98D4",
        "color4": "#5EA3DE",
        "color5": "#6EAFE8",
        "color6": "#91C8F9",
        "color7": "#cedbed",
        "color8": "#9099a5",
        "color9": "#446CAB",
        "color10": "#409FBC",
        "color11": "#4F98D4",
        "color12": "#5EA3DE",
        "color13": "#6EAFE8",
        "color14": "#91C8F9",
        "color15": "#cedbed"
    }
}