{
    "wallpaper": "/home/birkhoff/Images/unsplash/aaliya-wahab-iGG40UAAXwY-unsplash.jpg",
    "alpha": "100",
    "special": {
        "background": "#0F0E0F",
        "foreground": "#cac1bf",
        "cursor": "#cac1bf"
    },
    "colors": {
        "color0": "#0F0E0F",
        "color1": "#B12318",
        "color2": "#956925",
        "color3": "#8F7059",
        "color4": "#A4876E",
        "color5": "#CB9352",
        "color6": "#55928E",
        "color7": "#cac1bf",
        "color8": "#8d8785",
        "color9": "#B12318",
        "color10": "#956925",
        "color11": "#8F7059",
        "color12": "#A4876E",
        "color13": "#CB9352",
        "color14": "#55928E",
        "color15": "#cac1bf"
    }
}